pygments_lexer_pseudocode_fr/__init__.py
pygments_lexer_pseudocode_fr-0.1.15.dist-info/LICENSE
pygments_lexer_pseudocode_fr-0.1.15.dist-info/METADATA
pygments_lexer_pseudocode_fr-0.1.15.dist-info/WHEEL
pygments_lexer_pseudocode_fr-0.1.15.dist-info/entry_points.txt
pygments_lexer_pseudocode_fr-0.1.15.dist-info/top_level.txt
pygments_lexer_pseudocode_fr-0.1.15.dist-info/RECORD
