Metadata-Version: 2.1
Name: pygments-lexer-pseudocode-fr
Version: 0.1.15
Summary: Pygments Lexer for French Pseudocode
Home-page: https://gitlab.com/rod2ik/pygments-lexer-pseudocode-fr.git
Author: Rodrigo Schwencke
Author-email: rod2ik.dev@gmail.com
License: GPLv3+
Keywords: pygments lexer syntax highlight pseudo pseudocode algorithme algorithm fr
Platform: UNKNOWN
Classifier: Development Status :: 5 - Production/Stable
Classifier: Intended Audience :: Education
Classifier: Intended Audience :: End Users/Desktop
Classifier: Intended Audience :: Information Technology
Classifier: Intended Audience :: Science/Research
Classifier: Intended Audience :: Developers
Classifier: Topic :: Documentation
Classifier: Natural Language :: French
Classifier: Topic :: Text Processing
Classifier: Topic :: Utilities
Classifier: License :: OSI Approved :: GNU General Public License v3 or later (GPLv3+)
Classifier: Programming Language :: Python :: 3
Classifier: Programming Language :: Python :: 3.4
Classifier: Programming Language :: Python :: 3.5
Classifier: Programming Language :: Python :: 3.6
Classifier: Programming Language :: Python :: 3.7
Classifier: Programming Language :: Python :: 3.8
Classifier: Programming Language :: Python :: 3.9
Classifier: Programming Language :: Python :: 3.10
Classifier: Programming Language :: Python :: 3.11
Classifier: Operating System :: OS Independent
Classifier: Operating System :: POSIX :: Linux
Classifier: Operating System :: MacOS :: MacOS X
Classifier: Operating System :: Microsoft :: Windows :: Windows 10
License-File: LICENSE
Requires-Dist: pygments
